Workbook

Sheet Dashboard
A1: Dashboard
A3: Financial Modeling Toolkit
A4: Comprehensive Business Financial Planning
A7: KEY FINANCIAL METRICS
A9: Total Startup Costs: | B9: 10000
A10: Monthly Operating Expenses: | B10: 5000
A11: Break-even Point (Months): | B11: ='Break-even Analysis'!B10 -> 44.166667
A12: Funding Required: | B12: ='Funding Calculator'!B11 -> 150360

Sheet Startup Costs
A1: STARTUP COSTS CALCULATOR
A3: Category | B3: Description | C3: Amount | D3: Notes
A4: Legal & Professional | B4: Business registration, legal fees | C4: 2500 | D4: Varies by business structure
A5: Technology Setup | B5: Website, software, equipment | C5: 5000 | D5: Include no-code platform costs
A6: Marketing & Branding | B6: Logo, website, initial marketing | C6: 3000 | D6: Essential for customer acquisition
A7: Office & Equipment | B7: Workspace, furniture, supplies | C7: 4000 | D7: Consider remote work options
A8: Insurance | B8: Liability, professional, health | C8: 2000 | D8: Critical risk management
A9: Initial Inventory | B9: Product inventory or supplies | C9: 10000 | D9: If applicable to business model
A10: Working Capital | B10: Operating expenses buffer | C10: 15000 | D10: 3-6 months of expenses
A11: Licenses & Permits | B11: Required business licenses | C11: 500 | D11: Research local requirements
A12: Professional Services | B12: Accounting, consulting setup | C12: 1500 | D12: Essential professional support
A13: Contingency Fund | B13: Unexpected expenses | C13: 5000 | D13: 10-15% of total budget
A15: TOTAL STARTUP COSTS | C15: =SUM(C4:C13) -> 48500

Sheet Operating Expenses
A1: MONTHLY OPERATING EXPENSES
A3: Expense Category | B3: Description | C3: Monthly Amount | D3: Annual Amount
A4: Rent/Office Space | B4: Office rent or co-working | C4: 1500 | D4: =C4*12 -> 18000
A5: Utilities | B5: Internet, phone, electricity | C5: 200 | D5: =C5*12 -> 2400
A6: Software Subscriptions | B6: Business software, tools | C6: 300 | D6: =C6*12 -> 3600
A7: Marketing & Advertising | B7: Digital marketing, ads | C7: 1000 | D7: =C7*12 -> 12000
A8: Professional Services | B8: Legal, accounting, consulting | C8: 800 | D8: =C8*12 -> 9600
A9: Insurance | B9: Business insurance premiums | C9: 400 | D9: =C9*12 -> 4800
A10: Travel & Transportation | B10: Business travel, fuel | C10: 300 | D10: =C10*12 -> 3600
A11: Office Supplies | B11: Supplies, materials | C11: 150 | D11: =C11*12 -> 1800
A12: Telecommunications | B12: Phone, internet, communication | C12: 200 | D12: =C12*12 -> 2400
A13: Professional Development | B13: Training, courses, conferences | C13: 250 | D13: =C13*12 -> 3000
A14: Miscellaneous | B14: Other business expenses | C14: 200 | D14: =C14*12 -> 2400
A16: TOTAL MONTHLY EXPENSES | C16: =SUM(C4:C14) -> 5300 | D16: =SUM(D4:D14) -> 63600

Sheet Revenue Projections
A1: REVENUE PROJECTIONS
A3: Month | B3: Customers | C3: Avg Revenue/Customer | D3: Monthly Revenue | E3: Cumulative Revenue
A4: Month 1 | B4: 2 | C4: 150 | D4: =B4*C4 -> 300 | E4: =D4 -> 300
A5: Month 2 | B5: 4 | C5: 150 | D5: =B5*C5 -> 600 | E5: =D5+E4 -> 900
A6: Month 3 | B6: 6 | C6: 150 | D6: =B6*C6 -> 900 | E6: =D6+E5 -> 1800
A7: Month 4 | B7: 9 | C7: 150 | D7: =B7*C7 -> 1350 | E7: =D7+E6 -> 3150
A8: Month 5 | B8: 12 | C8: 150 | D8: =B8*C8 -> 1800 | E8: =D8+E7 -> 4950
A9: Month 6 | B9: 15 | C9: 150 | D9: =B9*C9 -> 2250 | E9: =D9+E8 -> 7200
A10: Month 7 | B10: 20 | C10: 150 | D10: =B10*C10 -> 3000 | E10: =D10+E9 -> 10200
A11: Month 8 | B11: 25 | C11: 150 | D11: =B11*C11 -> 3750 | E11: =D11+E10 -> 13950
A12: Month 9 | B12: 30 | C12: 150 | D12: =B12*C12 -> 4500 | E12: =D12+E11 -> 18450
A13: Month 10 | B13: 35 | C13: 150 | D13: =B13*C13 -> 5250 | E13: =D13+E12 -> 23700
A14: Month 11 | B14: 40 | C14: 150 | D14: =B14*C14 -> 6000 | E14: =D14+E13 -> 29700
A15: Month 12 | B15: 45 | C15: 150 | D15: =B15*C15 -> 6750 | E15: =D15+E14 -> 36450
A16: Month 13 | B16: 53 | C16: 150 | D16: =B16*C16 -> 7950 | E16: =D16+E15 -> 44400
... A27: Month 24 | B27: 141 | C27: 150 | D27: =B27*C27 -> 21150 | E27: =D27+E26 -> 211050

Sheet Cash Flow Projections
A1: CASH FLOW PROJECTIONS
A3: Month | B3: Revenue | C3: Operating Expenses | D3: Net Cash Flow | E3: Cumulative Cash | F3: Cash Position
A4: Month 1 | B4: ='Revenue Projections'!D4 -> 300 | C4: ='Operating Expenses'!C$15 -> 0 | D4: =B4-C4 -> 300 | E4: =D4 -> 300 | F4: =50000+E4 -> 50300
A5: Month 2 | B5: ='Revenue Projections'!D5 -> 600 | C5: ='Operating Expenses'!C$15 -> 0 | D5: =B5-C5 -> 600 | E5: =D5+E4 -> 900 | F5: =F4+D5 -> 50900
A6: Month 3 | B6: ='Revenue Projections'!D6 -> 900 | C6: ='Operating Expenses'!C$15 -> 0 | D6: =B6-C6 -> 900 | E6: =D6+E5 -> 1800 | F6: =F5+D6 -> 51800
A7: Month 4 | B7: ='Revenue Projections'!D7 -> 1350 | C7: ='Operating Expenses'!C$15 -> 0 | D7: =B7-C7 -> 1350 | E7: =D7+E6 -> 3150 | F7: =F6+D7 -> 53150
A8: Month 5 | B8: ='Revenue Projections'!D8 -> 1800 | C8: ='Operating Expenses'!C$15 -> 0 | D8: =B8-C8 -> 1800 | E8: =D8+E7 -> 4950 | F8: =F7+D8 -> 54950
A9: Month 6 | B9: ='Revenue Projections'!D9 -> 2250 | C9: ='Operating Expenses'!C$15 -> 0 | D9: =B9-C9 -> 2250 | E9: =D9+E8 -> 7200 | F9: =F8+D9 -> 57200
A10: Month 7 | B10: ='Revenue Projections'!D10 -> 3000 | C10: ='Operating Expenses'!C$15 -> 0 | D10: =B10-C10 -> 3000 | E10: =D10+E9 -> 10200 | F10: =F9+D10 -> 60200
A11: Month 8 | B11: ='Revenue Projections'!D11 -> 3750 | C11: ='Operating Expenses'!C$15 -> 0 | D11: =B11-C11 -> 3750 | E11: =D11+E10 -> 13950 | F11: =F10+D11 -> 63950
A12: Month 9 | B12: ='Revenue Projections'!D12 -> 4500 | C12: ='Operating Expenses'!C$15 -> 0 | D12: =B12-C12 -> 4500 | E12: =D12+E11 -> 18450 | F12: =F11+D12 -> 68450
A13: Month 10 | B13: ='Revenue Projections'!D13 -> 5250 | C13: ='Operating Expenses'!C$15 -> 0 | D13: =B13-C13 -> 5250 | E13: =D13+E12 -> 23700 | F13: =F12+D13 -> 73700
A14: Month 11 | B14: ='Revenue Projections'!D14 -> 6000 | C14: ='Operating Expenses'!C$15 -> 0 | D14: =B14-C14 -> 6000 | E14: =D14+E13 -> 29700 | F14: =F13+D14 -> 79700
A15: Month 12 | B15: ='Revenue Projections'!D15 -> 6750 | C15: ='Operating Expenses'!C$15 -> 0 | D15: =B15-C15 -> 6750 | E15: =D15+E14 -> 36450 | F15: =F14+D15 -> 86450
A16: Month 13 | B16: ='Revenue Projections'!D16 -> 7950 | C16: ='Operating Expenses'!C$15 -> 0 | D16: =B16-C16 -> 7950 | E16: =D16+E15 -> 44400 | F16: =F15+D16 -> 94400
... A27: Month 24 | B27: ='Revenue Projections'!D27 -> 21150 | C27: ='Operating Expenses'!C$15 -> 0 | D27: =B27-C27 -> 21150 | E27: =D27+E26 -> 211050 | F27: =F26+D27 -> 261050

Sheet Break-even Analysis
A1: BREAK-EVEN ANALYSIS
A3: BREAK-EVEN CALCULATION
A5: Fixed Monthly Costs: | B5: ='Operating Expenses'!C$16 -> 5300
A6: Average Revenue per Customer: | B6: 150
A7: Variable Cost per Customer: | B7: 30
A8: Contribution Margin per Customer: | B8: =B6-B7 -> 120
A10: Break-even Customers per Month: | B10: =B5/B8 -> 44.166667
A11: Break-even Revenue per Month: | B11: =B10*B6 -> 6625

Sheet Funding Calculator
A1: FUNDING REQUIREMENTS CALCULATOR
A3: FUNDING CALCULATION
A5: Startup Costs: | B5: ='Startup Costs'!C$15 -> 48500
A6: Working Capital (6 months): | B6: ='Operating Expenses'!C$16*6 -> 31800
A7: Personal Living Expenses (6 months): | B7: 30000
A8: Marketing & Growth Capital: | B8: 15000
A9: Contingency (20%): | B9: =(B5+B6+B7+B8)*0.2 -> 25060
A11: TOTAL FUNDING REQUIRED: | B11: =SUM(B5:B9) -> 150360

Sheet Scenario Analysis
A1: SCENARIO ANALYSIS
A3: Scenario | B3: Revenue Growth Rate | C3: Customer Acquisition | D3: Break-even Month | E3: Funding Required
A4: Conservative | B4: 10% | C4: Slow | D4: 18 | E4: 75000
A5: Realistic | B5: 25% | C5: Moderate | D5: 12 | E5: 60000
A6: Optimistic | B6: 50% | C6: Fast | D6: 8 | E6: 45000
A8: Funding Source Evaluation
A9: Bootstrap funding capacity assessed
A10: Traditional lending options researched
A11: Alternative funding sources explored
A12: Investment capital requirements understood
A13: Funding timeline and milestones established
A14: Backup funding plans developed

Sheet Resource Directory
A1: Resource Directory
A3: Government Resources
A4: SCORE Mentoring: www.score.org
A5: Small Business Development Centers: www.sba.gov/sbdc
A6: Women’s Business Centers: www.sba.gov/wbc
A7: Minority Business Development Agency: www.mbda.gov
A8: Traditional Lenders
A9: Community Banks: Local and regional banks
A10: Credit Unions: Member-owned financial cooperatives
A11: SBA Preferred Lenders: Banks with streamlined SBA processes
A12: Equipment Financing Companies: Specialized equipment lenders
A13: Commercial Finance Companies: Alternative commercial lenders
... A25: Insurance Agents: Business and personal insurance coverage
